//Deobfuscated with https://github.com/SimplyProgrammer/Minecraft-Deobfuscator3000 using mappings "E:\cocaine"!

//Decompiled by Procyon!

package com.mrzak34.thunderhack.command;

import java.util.*;

public class Commands
{
    public static ArrayList<Command> command_list;
    static HashMap<String, Command> list_command;
    public static final ThunderString prefix;
    
    public Commands() {
        // 
        // This method could not be decompiled.
        // 
        // Original Bytecode:
        // 
        //     1: invokespecial   java/lang/Object.<init>:()V
        //     4: new             new            !!! ERROR
        //     7: dup            
        //     8: invokespecial   invokespecial  !!! ERROR
        //    11: invokestatic    com/mrzak34/thunderhack/command/Commands.add_command:(Lcom/mrzak34/thunderhack/command/Command;)V
        //    14: getstatic       com/mrzak34/thunderhack/command/Commands.command_list:Ljava/util/ArrayList;
        //    17: invokedynamic   BootstrapMethod #0, apply:()Ljava/util/function/Function;
        //    22: invokestatic    java/util/Comparator.comparing:(Ljava/util/function/Function;)Ljava/util/Comparator;
        //    25: invokevirtual   java/util/ArrayList.sort:(Ljava/util/Comparator;)V
        //    28: return         
        // 
        // The error that occurred was:
        // 
        // java.lang.IllegalStateException: Invalid BootstrapMethods attribute entry: 2 additional arguments required for method java/lang/invoke/StringConcatFactory.makeConcatWithConstants, but only 1 specified.
        //     at com.strobel.assembler.ir.Error.invalidBootstrapMethodEntry(Error.java:244)
        //     at com.strobel.assembler.ir.MetadataReader.readAttributeCore(MetadataReader.java:280)
        //     at com.strobel.assembler.metadata.ClassFileReader.readAttributeCore(ClassFileReader.java:261)
        //     at com.strobel.assembler.ir.MetadataReader.inflateAttributes(MetadataReader.java:439)
        //     at com.strobel.assembler.metadata.ClassFileReader.visitAttributes(ClassFileReader.java:1134)
        //     at com.strobel.assembler.metadata.ClassFileReader.readClass(ClassFileReader.java:439)
        //     at com.strobel.assembler.metadata.ClassFileReader.readClass(ClassFileReader.java:377)
        //     at com.strobel.assembler.metadata.MetadataSystem.resolveType(MetadataSystem.java:129)
        //     at com.strobel.assembler.metadata.MetadataSystem.resolveCore(MetadataSystem.java:81)
        //     at com.strobel.assembler.metadata.MetadataResolver.resolve(MetadataResolver.java:104)
        //     at com.strobel.assembler.metadata.CoreMetadataFactory$UnresolvedType.resolve(CoreMetadataFactory.java:616)
        //     at com.strobel.assembler.metadata.MetadataResolver.resolve(MetadataResolver.java:128)
        //     at com.strobel.assembler.metadata.CoreMetadataFactory$UnresolvedType.resolve(CoreMetadataFactory.java:626)
        //     at com.strobel.assembler.metadata.MethodReference.resolve(MethodReference.java:177)
        //     at com.strobel.decompiler.ast.TypeAnalysis.inferCall(TypeAnalysis.java:2438)
        //     at com.strobel.decompiler.ast.TypeAnalysis.doInferTypeForExpression(TypeAnalysis.java:1029)
        //     at com.strobel.decompiler.ast.TypeAnalysis.inferTypeForExpression(TypeAnalysis.java:803)
        //     at com.strobel.decompiler.ast.TypeAnalysis.runInference(TypeAnalysis.java:672)
        //     at com.strobel.decompiler.ast.TypeAnalysis.runInference(TypeAnalysis.java:655)
        //     at com.strobel.decompiler.ast.TypeAnalysis.runInference(TypeAnalysis.java:365)
        //     at com.strobel.decompiler.ast.TypeAnalysis.run(TypeAnalysis.java:96)
        //     at com.strobel.decompiler.ast.AstOptimizer.optimize(AstOptimizer.java:109)
        //     at com.strobel.decompiler.ast.AstOptimizer.optimize(AstOptimizer.java:42)
        //     at com.strobel.decompiler.languages.java.ast.AstMethodBodyBuilder.createMethodBody(AstMethodBodyBuilder.java:214)
        //     at com.strobel.decompiler.languages.java.ast.AstMethodBodyBuilder.createMethodBody(AstMethodBodyBuilder.java:99)
        //     at com.strobel.decompiler.languages.java.ast.AstBuilder.createMethodBody(AstBuilder.java:782)
        //     at com.strobel.decompiler.languages.java.ast.AstBuilder.createConstructor(AstBuilder.java:713)
        //     at com.strobel.decompiler.languages.java.ast.AstBuilder.addTypeMembers(AstBuilder.java:549)
        //     at com.strobel.decompiler.languages.java.ast.AstBuilder.createTypeCore(AstBuilder.java:519)
        //     at com.strobel.decompiler.languages.java.ast.AstBuilder.createTypeNoCache(AstBuilder.java:161)
        //     at com.strobel.decompiler.languages.java.ast.AstBuilder.createType(AstBuilder.java:150)
        //     at com.strobel.decompiler.languages.java.ast.AstBuilder.addType(AstBuilder.java:125)
        //     at com.strobel.decompiler.languages.java.JavaLanguage.buildAst(JavaLanguage.java:71)
        //     at com.strobel.decompiler.languages.java.JavaLanguage.decompileType(JavaLanguage.java:59)
        //     at com.strobel.decompiler.Decompiler.decompile(Decompiler.java:70)
        //     at org.ugp.mc.deobfuscator.Deobfuscator3000.decompile(Deobfuscator3000.java:538)
        //     at org.ugp.mc.deobfuscator.Deobfuscator3000.decompileAndDeobfuscate(Deobfuscator3000.java:552)
        //     at org.ugp.mc.deobfuscator.Deobfuscator3000.processMod(Deobfuscator3000.java:510)
        //     at org.ugp.mc.deobfuscator.Deobfuscator3000.lambda$21(Deobfuscator3000.java:329)
        //     at java.lang.Thread.run(Unknown Source)
        // 
        throw new IllegalStateException("An error occurred while decompiling this method.");
    }
    
    public static void add_command(final Command command) {
        Commands.command_list.add(command);
        Commands.list_command.put(command.get_name().toLowerCase(), command);
    }
    
    public String[] get_message(final String message) {
        String[] arguments = new String[0];
        if (this.has_prefix(message)) {
            arguments = message.replaceFirst(Commands.prefix.get_value(), "").split(" ");
        }
        return arguments;
    }
    
    public boolean has_prefix(final String message) {
        return message.startsWith(Commands.prefix.get_value());
    }
    
    public void set_prefix(final String new_prefix) {
        Commands.prefix.set_value(new_prefix);
    }
    
    public String get_prefix() {
        return Commands.prefix.get_value();
    }
    
    public static ArrayList<Command> get_pure_command_list() {
        return Commands.command_list;
    }
    
    public static Command get_command_with_name(final String name) {
        return Commands.list_command.get(name.toLowerCase());
    }
    
    static {
        Commands.command_list = new ArrayList<Command>();
        Commands.list_command = new HashMap<String, Command>();
        prefix = new ThunderString("Prefix", "Prefix", ".");
    }
}
