//Deobfuscated with https://github.com/SimplyProgrammer/Minecraft-Deobfuscator3000 using mappings "E:\cocaine"!

//Decompiled by Procyon!

package com.mrzak34.thunderhack.module.modules.misc;

import com.mrzak34.thunderhack.module.*;
import com.mrzak34.thunderhack.settings.*;

public class Freez extends Module
{
    NumberSetting freezValue;
    
    public Freez() {
        super("Freez", 0, false, Category.MISC);
        this.freezValue = new NumberSetting("freez", 1000.0f, 0.0f, 1000.0f, false);
        this.addSettings(new Setting[] { this.freezValue });
    }
    
    public void onEnable() {
        // 
        // This method could not be decompiled.
        // 
        // Original Bytecode:
        // 
        //     1: invokespecial   com/mrzak34/thunderhack/module/Module.onEnable:()V
        //     4: ldc             "sleep"
        //     6: invokestatic    invokestatic   !!! ERROR
        //     9: aload_0         /* this */
        //    10: getfield        com/mrzak34/thunderhack/module/modules/misc/Freez.freezValue:Lcom/mrzak34/thunderhack/settings/NumberSetting;
        //    13: invokevirtual   com/mrzak34/thunderhack/settings/NumberSetting.getValue:()D
        //    16: d2l            
        //    17: invokestatic    java/lang/Thread.sleep:(J)V
        //    20: goto            24
        //    23: astore_1       
        //    24: return         
        //    StackMapTable: 00 02 57 07 00 29 00
        //    Exceptions:
        //  Try           Handler
        //  Start  End    Start  End    Type                            
        //  -----  -----  -----  -----  --------------------------------
        //  4      20     23     24     Ljava/lang/InterruptedException;
        // 
        // The error that occurred was:
        // 
        // java.lang.IllegalStateException: Invalid BootstrapMethods attribute entry: 2 additional arguments required for method java/lang/invoke/StringConcatFactory.makeConcatWithConstants, but only 1 specified.
        //     at com.strobel.assembler.ir.Error.invalidBootstrapMethodEntry(Error.java:244)
        //     at com.strobel.assembler.ir.MetadataReader.readAttributeCore(MetadataReader.java:280)
        //     at com.strobel.assembler.metadata.ClassFileReader.readAttributeCore(ClassFileReader.java:261)
        //     at com.strobel.assembler.ir.MetadataReader.inflateAttributes(MetadataReader.java:439)
        //     at com.strobel.assembler.metadata.ClassFileReader.visitAttributes(ClassFileReader.java:1134)
        //     at com.strobel.assembler.metadata.ClassFileReader.readClass(ClassFileReader.java:439)
        //     at com.strobel.assembler.metadata.ClassFileReader.readClass(ClassFileReader.java:377)
        //     at com.strobel.assembler.metadata.MetadataSystem.resolveType(MetadataSystem.java:129)
        //     at com.strobel.assembler.metadata.MetadataSystem.resolveCore(MetadataSystem.java:81)
        //     at com.strobel.assembler.metadata.MetadataResolver.resolve(MetadataResolver.java:104)
        //     at com.strobel.assembler.metadata.CoreMetadataFactory$UnresolvedType.resolve(CoreMetadataFactory.java:616)
        //     at com.strobel.assembler.metadata.MetadataResolver.resolve(MetadataResolver.java:128)
        //     at com.strobel.assembler.metadata.CoreMetadataFactory$UnresolvedType.resolve(CoreMetadataFactory.java:626)
        //     at com.strobel.assembler.metadata.MethodReference.resolve(MethodReference.java:177)
        //     at com.strobel.decompiler.ast.TypeAnalysis.inferCall(TypeAnalysis.java:2438)
        //     at com.strobel.decompiler.ast.TypeAnalysis.doInferTypeForExpression(TypeAnalysis.java:1029)
        //     at com.strobel.decompiler.ast.TypeAnalysis.inferTypeForExpression(TypeAnalysis.java:803)
        //     at com.strobel.decompiler.ast.TypeAnalysis.runInference(TypeAnalysis.java:672)
        //     at com.strobel.decompiler.ast.TypeAnalysis.runInference(TypeAnalysis.java:655)
        //     at com.strobel.decompiler.ast.TypeAnalysis.runInference(TypeAnalysis.java:365)
        //     at com.strobel.decompiler.ast.TypeAnalysis.run(TypeAnalysis.java:96)
        //     at com.strobel.decompiler.ast.AstOptimizer.optimize(AstOptimizer.java:109)
        //     at com.strobel.decompiler.ast.AstOptimizer.optimize(AstOptimizer.java:42)
        //     at com.strobel.decompiler.languages.java.ast.AstMethodBodyBuilder.createMethodBody(AstMethodBodyBuilder.java:214)
        //     at com.strobel.decompiler.languages.java.ast.AstMethodBodyBuilder.createMethodBody(AstMethodBodyBuilder.java:99)
        //     at com.strobel.decompiler.languages.java.ast.AstBuilder.createMethodBody(AstBuilder.java:782)
        //     at com.strobel.decompiler.languages.java.ast.AstBuilder.createMethod(AstBuilder.java:675)
        //     at com.strobel.decompiler.languages.java.ast.AstBuilder.addTypeMembers(AstBuilder.java:552)
        //     at com.strobel.decompiler.languages.java.ast.AstBuilder.createTypeCore(AstBuilder.java:519)
        //     at com.strobel.decompiler.languages.java.ast.AstBuilder.createTypeNoCache(AstBuilder.java:161)
        //     at com.strobel.decompiler.languages.java.ast.AstBuilder.createType(AstBuilder.java:150)
        //     at com.strobel.decompiler.languages.java.ast.AstBuilder.addType(AstBuilder.java:125)
        //     at com.strobel.decompiler.languages.java.JavaLanguage.buildAst(JavaLanguage.java:71)
        //     at com.strobel.decompiler.languages.java.JavaLanguage.decompileType(JavaLanguage.java:59)
        //     at com.strobel.decompiler.Decompiler.decompile(Decompiler.java:70)
        //     at org.ugp.mc.deobfuscator.Deobfuscator3000.decompile(Deobfuscator3000.java:538)
        //     at org.ugp.mc.deobfuscator.Deobfuscator3000.decompileAndDeobfuscate(Deobfuscator3000.java:552)
        //     at org.ugp.mc.deobfuscator.Deobfuscator3000.processMod(Deobfuscator3000.java:510)
        //     at org.ugp.mc.deobfuscator.Deobfuscator3000.lambda$21(Deobfuscator3000.java:329)
        //     at java.lang.Thread.run(Unknown Source)
        // 
        throw new IllegalStateException("An error occurred while decompiling this method.");
    }
}
